converter/__init__.py
converter/element.py
converter/graph.py
converter/mixins.py
graphml2svg/__init__.py
graphml2svg/element.py
graphml2svg/graph.py
graphml2svg/mixins.py
graphml2svg-0.0.4.dist-info/LICENSE
graphml2svg-0.0.4.dist-info/METADATA
graphml2svg-0.0.4.dist-info/WHEEL
graphml2svg-0.0.4.dist-info/top_level.txt
graphml2svg-0.0.4.dist-info/RECORD
