Metadata-Version: 2.1
Name: graphml2svg
Version: 0.0.4
Summary: YFile .graphml converter to .svg
Home-page: https://github.com/alex-fe/Graphml-to-SVG-converter
Author: Alex Feldman
Author-email: alexfeldman93@gmail.com
License: MIT
Platform: UNKNOWN
Classifier: Programming Language :: Python :: 3
Classifier: License :: OSI Approved :: MIT License
Classifier: Operating System :: OS Independent
Requires-Dist: svgwrite
